{
    "@class": "com.kony.gen.viz.model.component.KVizImage2",
    "DNDConfig": null,
    "__parentReadjusting__": false,
    "_base64_": null,
    "_height_": {
        "type": "string",
        "value": "100%"
    },
    "_left_": {
        "type": "string",
        "value": "0dp"
    },
    "_margin_": [
        0,
        0,
        0,
        0
    ],
    "_padding_": [
        0,
        0,
        0,
        0
    ],
    "_skin_": "s1f502b97c1a495f95954d96878c8763",
    "_src_": "imagedrag.png",
    "_top_": {
        "type": "string",
        "value": "0dp"
    },
    "_width_": {
        "type": "string",
        "value": "100%"
    },
    "canUpdateUI": true,
    "centerx": {
        "type": "string",
        "value": "50%"
    },
    "centery": {
        "type": "string",
        "value": "50%"
    },
    "containerId": true,
    "containerweight": 100,
    "context": {
        "channel": "mobile",
        "formID": "FBox0bc0135f276ee47",
        "templateType": "segments",
        "topLevelBox": null
    },
    "id": "oppurtinitiesImg",
    "imagescalemode": 1,
    "info": null,
    "isSegmentChild": true,
    "isvisible": true,
    "kuid": "fff2662877ff418ba23661ea3492fd4a",
    "name": "kony.ui.Image2",
    "parent": "oppurtinitiesImgCont",
    "pf": "FBox0bc0135f276ee47",
    "srcType": 1,
    "wType": "Image",
    "widgetalignment": 5,
    "zindex": 3
}