{
    "AS_Form_8f9814958986405f9cceff656c607bc1": {
        "id": "AS_Form_8f9814958986405f9cceff656c607bc1",
        "type": "ACTION_SEQUENCE",
        "params": [{
            "datatype": "collection",
            "name": "eventobject"
        }],
        "contextObj": {
            "name": "frmLogin",
            "type": "forms",
            "platform": "",
            "KUID": "0c84fe69a75f4b178ea060e1ae667f33"
        },
        "actions": [{
            "id": "INVOKE_FUNCTION___6f290d0ca16148caa5ede7937c52237b",
            "type": "INVOKE_FUNCTION",
            "sequenceKUID": "MbaasInit",
            "display": "MbaasInit",
            "inputparams": [],
            "parentId": null,
            "callbackType": null
        }]
    }
}